[
	{
		"inputs": [
			{
				"internalType": "address",
				"name": "addr",
				"type": "address"
			},
			{
				"internalType": "uint256",
				"name": "_licence",
				"type": "uint256"
			},
			{
				"internalType": "uint256",
				"name": "id",
				"type": "uint256"
			}
		],
		"name": "buy",
		"outputs": [],
		"stateMutability": "nonpayable",
		"type": "function"
	},
	{
		"inputs": [
			{
				"internalType": "uint256",
				"name": "id",
				"type": "uint256"
			},
			{
				"internalType": "uint256",
				"name": "licence",
				"type": "uint256"
			},
			{
				"internalType": "address",
				"name": "s",
				"type": "address"
			}
		],
		"name": "ChangeOwnere",
		"outputs": [],
		"stateMutability": "nonpayable",
		"type": "function"
	},
	{
		"inputs": [
			{
				"internalType": "uint256",
				"name": "id",
				"type": "uint256"
			}
		],
		"name": "delItem",
		"outputs": [],
		"stateMutability": "nonpayable",
		"type": "function"
	},
	{
		"inputs": [
			{
				"internalType": "string",
				"name": "_type",
				"type": "string"
			},
			{
				"internalType": "uint256",
				"name": "_rs",
				"type": "uint256"
			},
			{
				"internalType": "string",
				"name": "_name",
				"type": "string"
			},
			{
				"internalType": "string",
				"name": "About",
				"type": "string"
			},
			{
				"internalType": "string",
				"name": "image",
				"type": "string"
			}
		],
		"name": "makeProd",
		"outputs": [],
		"stateMutability": "nonpayable",
		"type": "function"
	},
	{
		"inputs": [],
		"stateMutability": "nonpayable",
		"type": "constructor"
	},
	{
		"inputs": [
			{
				"internalType": "uint256",
				"name": "id",
				"type": "uint256"
			}
		],
		"name": "check",
		"outputs": [
			{
				"components": [
					{
						"internalType": "string",
						"name": "typeOf",
						"type": "string"
					},
					{
						"internalType": "uint256",
						"name": "id",
						"type": "uint256"
					},
					{
						"internalType": "uint256",
						"name": "Rs",
						"type": "uint256"
					},
					{
						"internalType": "string",
						"name": "name",
						"type": "string"
					},
					{
						"internalType": "uint256",
						"name": "LicenseNoOfHolder",
						"type": "uint256"
					},
					{
						"internalType": "address",
						"name": "HoldersAddress",
						"type": "address"
					},
					{
						"internalType": "string",
						"name": "WhatAboutUniqueInProduct",
						"type": "string"
					},
					{
						"internalType": "string",
						"name": "image",
						"type": "string"
					}
				],
				"internalType": "struct OrigProduct.product[]",
				"name": "",
				"type": "tuple[]"
			}
		],
		"stateMutability": "view",
		"type": "function"
	},
	{
		"inputs": [],
		"name": "seeItemCom",
		"outputs": [
			{
				"components": [
					{
						"internalType": "string",
						"name": "typeOf",
						"type": "string"
					},
					{
						"internalType": "uint256",
						"name": "id",
						"type": "uint256"
					},
					{
						"internalType": "uint256",
						"name": "Rs",
						"type": "uint256"
					},
					{
						"internalType": "string",
						"name": "name",
						"type": "string"
					},
					{
						"internalType": "uint256",
						"name": "LicenseNoOfHolder",
						"type": "uint256"
					},
					{
						"internalType": "address",
						"name": "HoldersAddress",
						"type": "address"
					},
					{
						"internalType": "string",
						"name": "WhatAboutUniqueInProduct",
						"type": "string"
					},
					{
						"internalType": "string",
						"name": "image",
						"type": "string"
					}
				],
				"internalType": "struct OrigProduct.product[]",
				"name": "",
				"type": "tuple[]"
			}
		],
		"stateMutability": "view",
		"type": "function"
	},
	{
		"inputs": [],
		"name": "seeItemhol",
		"outputs": [
			{
				"components": [
					{
						"internalType": "string",
						"name": "typeOf",
						"type": "string"
					},
					{
						"internalType": "uint256",
						"name": "id",
						"type": "uint256"
					},
					{
						"internalType": "uint256",
						"name": "Rs",
						"type": "uint256"
					},
					{
						"internalType": "string",
						"name": "name",
						"type": "string"
					},
					{
						"internalType": "uint256",
						"name": "LicenseNoOfHolder",
						"type": "uint256"
					},
					{
						"internalType": "address",
						"name": "HoldersAddress",
						"type": "address"
					},
					{
						"internalType": "string",
						"name": "WhatAboutUniqueInProduct",
						"type": "string"
					},
					{
						"internalType": "string",
						"name": "image",
						"type": "string"
					}
				],
				"internalType": "struct OrigProduct.product[]",
				"name": "",
				"type": "tuple[]"
			}
		],
		"stateMutability": "view",
		"type": "function"
	}
]